pt_svr/__init__.py
pt_svr/render.py
pytorch_semantic_volume_render-0.0.1.dist-info/LICENSE
pytorch_semantic_volume_render-0.0.1.dist-info/METADATA
pytorch_semantic_volume_render-0.0.1.dist-info/WHEEL
pytorch_semantic_volume_render-0.0.1.dist-info/top_level.txt
pytorch_semantic_volume_render-0.0.1.dist-info/RECORD
